{
  "objects": {
    "data": [
      {
        "properties": {
          "mode": {
            "expr": {
              "Literal": {
                "Value": "'Dropdown'"
              }
            }
          }
        }
      }
    ],
    "general": [
      {
        "properties": {
          "filter": {
            "filter": {
              "Version": 2,
              "From": [
                {
                  "Name": "d",
                  "Entity": "Data",
                  "Type": 0
                }
              ],
              "Where": [
                {
                  "Condition": {
                    "In": {
                      "Expressions": [
                        {
                          "Column": {
                            "Expression": {
                              "SourceRef": {
                                "Source": "d"
                              }
                            },
                            "Property": "Quarter"
                          }
                        }
                      ],
                      "Values": [
                        [
                          {
                            "Literal": {
                              "Value": "'2023Q2'"
                            }
                          }
                        ]
                      ]
                    }
                  }
                }
              ]
            }
          }
        }
      }
    ],
    "selection": [
      {
        "properties": {
          "strictSingleSelect": {
            "expr": {
              "Literal": {
                "Value": "true"
              }
            }
          }
        }
      }
    ],
    "header": [
      {
        "properties": {
          "fontColor": {
            "solid": {
              "color": {
                "expr": {
                  "Literal": {
                    "Value": "'#DF542A'"
                  }
                }
              }
            }
          },
          "fontFamily": {
            "expr": {
              "Literal": {
                "Value": "'Arial'"
              }
            }
          },
          "text": {
            "expr": {
              "Literal": {
                "Value": "'Select Quarter'"
              }
            }
          },
          "bold": {
            "expr": {
              "Literal": {
                "Value": "true"
              }
            }
          }
        }
      }
    ],
    "items": [
      {
        "properties": {
          "background": {
            "solid": {
              "color": {
                "expr": {
                  "Literal": {
                    "Value": "'#DF542A'"
                  }
                }
              }
            }
          },
          "fontColor": {
            "solid": {
              "color": {
                "expr": {
                  "ThemeDataColor": {
                    "ColorId": 0,
                    "Percent": 0
                  }
                }
              }
            }
          },
          "bold": {
            "expr": {
              "Literal": {
                "Value": "true"
              }
            }
          }
        }
      }
    ],
    "pendingChangesIcon": [
      {
        "properties": {
          "show": {
            "expr": {
              "Literal": {
                "Value": "false"
              }
            }
          }
        }
      }
    ]
  },
  "projectionOrdering": {
    "Values": [
      0
    ]
  },
  "projectionActiveItems": {
    "Values": [
      {
        "queryRef": "Data.Quarter",
        "suppressConcat": false
      }
    ]
  },
  "queryMetadata": {
    "Select": [
      {
        "Restatement": "Quarter",
        "Name": "Data.Quarter",
        "Type": 2048
      }
    ]
  },
  "visualElements": [
    {
      "DataRoles": [
        {
          "Name": "Values",
          "Projection": 0,
          "isActive": true
        }
      ]
    }
  ],
  "selects": [
    {
      "displayName": "Quarter",
      "queryName": "Data.Quarter",
      "roles": {
        "Values": true
      },
      "type": {
        "category": null,
        "underlyingType": 1
      },
      "expr": {
        "Column": {
          "Expression": {
            "SourceRef": {
              "Entity": "Data"
            }
          },
          "Property": "Quarter"
        }
      }
    }
  ]
}