{
  "filters": {
    "byExpr": [
      {
        "type": "Advanced",
        "expression": {
          "Aggregation": {
            "Expression": {
              "Column": {
                "Expression": {
                  "SourceRef": {
                    "Entity": "Data"
                  }
                },
                "Property": "Attained Sales"
              }
            },
            "Function": 0
          }
        },
        "howCreated": 0
      },
      {
        "type": "Advanced",
        "expression": {
          "Column": {
            "Expression": {
              "SourceRef": {
                "Entity": "Data"
              }
            },
            "Property": "Week number"
          }
        },
        "howCreated": 0
      }
    ]
  },
  "singleVisual": {
    "visualType": "stackedAreaChart",
    "objects": {},
    "orderBy": [
      {
        "Direction": 1,
        "Expression": {
          "Column": {
            "Expression": {
              "SourceRef": {
                "Entity": "Data"
              }
            },
            "Property": "Week number"
          }
        }
      }
    ],
    "activeProjections": {
      "Category": [
        {
          "Column": {
            "Expression": {
              "SourceRef": {
                "Entity": "Data"
              }
            },
            "Property": "Week number"
          }
        }
      ]
    }
  }
}